sam_pytools/__init__.py
sam_pytools-0.1.3.dist-info/LICENSE.txt
sam_pytools-0.1.3.dist-info/METADATA
sam_pytools-0.1.3.dist-info/WHEEL
sam_pytools-0.1.3.dist-info/top_level.txt
sam_pytools-0.1.3.dist-info/RECORD
