Metadata-Version: 2.1
Name: sam_pytools
Version: 0.1.3
Summary: sam_pytools is a collection of Python utilities that provide commonly used functions, so we do not need to write
Home-page: https://github.com/humblesami/sam-djtools.git
Author-email: Sami Akram <eagle.ciit@gmail.com>
Maintainer-email: Sami Akram <eagle.ciit@gmail.com>
Project-URL: Changelog, https://github.com/humblesami/pyutils/CHANGES.rst
Project-URL: Code, https://github.com/humblesami/pyutils
Project-URL: Issue tracker, https://github.com/humblesami/pyutils/issues
Keywords: urllib,httplib,http
Classifier: Operating System :: OS Independent
Classifier: License :: OSI Approved :: MIT License
Classifier: Programming Language :: Python :: 3
Requires-Python: >=3
License-File: LICENSE.txt
Requires-Dist: python-dateutil>=2.9.0
Requires-Dist: pytz>=2024.2
Requires-Dist: requests>=2.32.2
